countpy/__init__.py
countpy/countpy.py
countpy/data/__init__.py
countpy/data/gatsby.txt
countpy/datasets.py
countpy/plotting.py
countpy-0.3.0.dist-info/LICENSE
countpy-0.3.0.dist-info/METADATA
countpy-0.3.0.dist-info/WHEEL
countpy-0.3.0.dist-info/RECORD
