Metadata-Version: 2.3
Name: countpy
Version: 0.3.0
Summary: A python package to help you count words in a text file
License: MIT
Author: Dalia Tavizon-Dykstra
Requires-Python: >=3.12
Classifier: License :: OSI Approved :: MIT License
Classifier: Programming Language :: Python :: 3
Classifier: Programming Language :: Python :: 3.12
Classifier: Programming Language :: Python :: 3.13
Requires-Dist: matplotlib (>=3.10.1)
